proto_man/__init__.py
proto_man/aaa/__init__.py
proto_man/common/ReqRep_pb2.py
proto_man/common/__init__.py
proto_man/common/metaData_pb2.py
proto_man/notify/__init__.py
proto_man/notify/message_pb2.py
proto_man-0.0.4.dist-info/METADATA
proto_man-0.0.4.dist-info/WHEEL
proto_man-0.0.4.dist-info/top_level.txt
proto_man-0.0.4.dist-info/RECORD
