Metadata-Version: 2.1
Name: proto-man
Version: 0.0.4
Summary: Protobuf repositories
Home-page: https://github.com/vogolabs/proto-man
Author: Surya Pradyumna
Author-email: surya.pradyumna@vogo.in
License: UNKNOWN
Platform: UNKNOWN
Classifier: License :: OSI Approved :: MIT License
Classifier: Operating System :: OS Independent
Requires-Dist: protobuf (>=3.8.0)
